gene_graph_lib/VF2_find_template.py
gene_graph_lib/__init__.py
gene_graph_lib/compute_complexity.py
gene_graph_lib/draw_graph.py
gene_graph_lib/find_context.py
gene_graph_lib/generate_subgraph.py
gene_graph_lib/pattern_searching.py
gene_graph_lib/reverse.py
gene_graph_lib-1.0.3.dist-info/LICENSE
gene_graph_lib-1.0.3.dist-info/METADATA
gene_graph_lib-1.0.3.dist-info/WHEEL
gene_graph_lib-1.0.3.dist-info/top_level.txt
gene_graph_lib-1.0.3.dist-info/RECORD
