Metadata-Version: 2.1
Name: gene-graph-lib
Version: 1.0.3
Summary: mini-library for GeneGraph tool and GCB project
Home-page: https://github.com/DNKonanov/gene_graph_lib
Author: DNKonanov
Author-email: konanovdmitriy@gmail.com
License: UNKNOWN
Platform: UNKNOWN
Classifier: Programming Language :: Python :: 3
Classifier: License :: OSI Approved :: MIT License
Classifier: Operating System :: OS Independent
